tsmodels/__init__.py
tsmodels/classes/__init__.py
tsmodels/classes/tsm_ARMA.py
tsmodels/classes/tsm_ARMA_GARCH.py
tsmodels/classes/tsm_LinearModel.py
tsmodels/classes/tsm_Prediction.py
tsmodels/classes/tsm_TSModel.py
tsmodels/data/apple_returns.csv
tsmodels/data/facebook_returns.csv
tsmodels/functions/__init__.py
tsmodels/functions/tsm_arma_acvf.py
tsmodels/functions/tsm_arma_garch_forecast.py
tsmodels/functions/tsm_arma_garch_obj_funs.py
tsmodels/functions/tsm_arma_obj_funs.py
tsmodels/functions/tsm_arma_to_ma.py
tsmodels/functions/tsm_densities.py
tsmodels/functions/tsm_format_ts.py
tsmodels/functions/tsm_get_data.py
tsmodels/functions/tsm_hannan_rissanen.py
tsmodels/functions/tsm_innov_alg.py
tsmodels/functions/tsm_ljung_box.py
tsmodels/functions/tsm_plot_acf.py
tsmodels/functions/tsm_sample_acvf.py
tsmodels/functions/tsm_solver.py
tsmodels/functions/tsm_yule_walker.py
tsmodels/settings/__init__.py
tsmodels/settings/tsm_settings.py
tsmodels-0.1.5.dist-info/METADATA
tsmodels-0.1.5.dist-info/RECORD
tsmodels-0.1.5.dist-info/WHEEL
tsmodels-0.1.5.dist-info/top_level.txt
