Metadata-Version: 2.1
Name: tsmodels
Version: 0.1.5
Summary: A package to build time series models.
Home-page: UNKNOWN
Author: Jack Dry
Author-email: jack_dry@outlook.com
License: UNKNOWN
Platform: UNKNOWN
Classifier: Programming Language :: Python :: 3
Classifier: Operating System :: OS Independent
